sloot.object-1.5.1-nspkg.pth
sloot/object/__init__.py
sloot/object/obj_utils.py
sloot.object-1.5.1.dist-info/DESCRIPTION.rst
sloot.object-1.5.1.dist-info/METADATA
sloot.object-1.5.1.dist-info/RECORD
sloot.object-1.5.1.dist-info/WHEEL
sloot.object-1.5.1.dist-info/metadata.json
sloot.object-1.5.1.dist-info/namespace_packages.txt
sloot.object-1.5.1.dist-info/pbr.json
sloot.object-1.5.1.dist-info/top_level.txt
