Metadata-Version: 2.0
Name: sloot.object
Version: 1.5.1
Summary: Object utils to make life easier
Home-page: https://github.com/samjy/sloot.object
Author: Samuel Jaillet
Author-email: sam+dev@samjy.com
License: MIT
Download-URL: https://github.com/samjy/sloot.object/tarball/1.5.1
Keywords: tools,object,utils,dict
Platform: any
Classifier: Development Status :: 4 - Beta
Classifier: License :: Freely Distributable
Classifier: Programming Language :: Python :: 2.7
Classifier: Programming Language :: Python :: 3.4
Classifier: Programming Language :: Python :: 3.5
Classifier: Programming Language :: Python :: 3.6
Classifier: Programming Language :: Python :: 3.7
Classifier: Topic :: Software Development
